{
  "modelVersion": "5.0.0",
  "name": "example",
  "version": "1.0.0",
  "description": "Please describe the basic information.",
  "main": "",
  "author": "",
  "license": "",
  "dependencies": {
    "@ohos/flutter_ohos": "file:./har/flutter.har",
    "@ohos/protobufjs": "^2.1.0",
    "long": "^5.2.1"
  },
  "devDependencies": {
    "@ohos/hypium": "1.0.6"
  },
  "overrides": {
    "@ohos/flutter_ohos": "file:./har/flutter.har",
    "barcode_scan2": "file:./har/barcode_scan2.har",
    "@ohos/flutter_module": "file:./entry"
  },
  "dynamicDependencies": {}
}